Metadata-Version: 2.1
Name: hellya-lite
Version: 15.0
Summary: Библиотека для программирования рисунков.
Home-page: https://github.com/Soviet-WorkShop/hellya_lite
Author: soviet_workshop
Author-email: soviet.workshop23@gmail.com
Keywords: soviet hellya pixel workshop drawing
Classifier: Programming Language :: Python :: 3.11
Classifier: License :: OSI Approved :: MIT License
Classifier: Operating System :: OS Independent
Requires-Python: >=3.9
